kili/__init__.py
kili/client.py
kili/client_domain.py
kili/exceptions.py
kili/plugins.py
kili/adapters/__init__.py
kili/adapters/authentification.py
kili/adapters/http_client.py
kili/adapters/kili_api_gateway/__init__.py
kili/adapters/kili_api_gateway/base.py
kili/adapters/kili_api_gateway/kili_api_gateway.py
kili/adapters/kili_api_gateway/api_key/__init__.py
kili/adapters/kili_api_gateway/api_key/mappers.py
kili/adapters/kili_api_gateway/api_key/operations.py
kili/adapters/kili_api_gateway/api_key/operations_mixin.py
kili/adapters/kili_api_gateway/asset/__init__.py
kili/adapters/kili_api_gateway/asset/formatters.py
kili/adapters/kili_api_gateway/asset/mappers.py
kili/adapters/kili_api_gateway/asset/operations.py
kili/adapters/kili_api_gateway/asset/operations_mixin.py
kili/adapters/kili_api_gateway/cloud_storage/__init__.py
kili/adapters/kili_api_gateway/cloud_storage/mappers.py
kili/adapters/kili_api_gateway/cloud_storage/operations.py
kili/adapters/kili_api_gateway/cloud_storage/types.py
kili/adapters/kili_api_gateway/event/__init__.py
kili/adapters/kili_api_gateway/event/mappers.py
kili/adapters/kili_api_gateway/event/operations.py
kili/adapters/kili_api_gateway/event/operations_mixin.py
kili/adapters/kili_api_gateway/event/queries.py
kili/adapters/kili_api_gateway/helpers/__init__.py
kili/adapters/kili_api_gateway/helpers/http_json.py
kili/adapters/kili_api_gateway/helpers/queries.py
kili/adapters/kili_api_gateway/issue/__init__.py
kili/adapters/kili_api_gateway/issue/mappers.py
kili/adapters/kili_api_gateway/issue/operations.py
kili/adapters/kili_api_gateway/issue/types.py
kili/adapters/kili_api_gateway/label/__init__.py
kili/adapters/kili_api_gateway/label/common.py
kili/adapters/kili_api_gateway/label/formatters.py
kili/adapters/kili_api_gateway/label/mappers.py
kili/adapters/kili_api_gateway/label/operations.py
kili/adapters/kili_api_gateway/label/operations_mixin.py
kili/adapters/kili_api_gateway/label/types.py
kili-26.1.2.dist-info/licenses/LICENSE.txt
kili-26.1.2.dist-info/METADATA
kili-26.1.2.dist-info/WHEEL
kili-26.1.2.dist-info/entry_points.txt
kili-26.1.2.dist-info/top_level.txt
kili-26.1.2.dist-info/RECORD
