Metadata-Version: 2.4
Name: kili
Version: 26.1.2
Summary: Python client for Kili Technology labeling tool
Author-email: Kili Technology <contact@kili-technology.com>
License: 
Project-URL: homepage, https://github.com/kili-technology/kili-python-sdk
Classifier: Intended Audience :: Science/Research
Classifier: Intended Audience :: Developers
Classifier: License :: OSI Approved :: Apache Software License
Classifier: Programming Language :: Python
Classifier: Topic :: Software Development
Classifier: Topic :: Scientific/Engineering
Classifier: Operating System :: Microsoft :: Windows
Classifier: Operating System :: POSIX
Classifier: Operating System :: Unix
Classifier: Operating System :: MacOS
Classifier: Programming Language :: Python :: 3
Classifier: Programming Language :: Python :: 3.10
Classifier: Programming Language :: Python :: 3.11
Classifier: Programming Language :: Python :: 3.12
Classifier: Programming Language :: Python :: 3.13
Classifier: Programming Language :: Python :: Implementation :: CPython
Classifier: Programming Language :: Python :: Implementation :: PyPy
Requires-Python: >=3.10
License-File: LICENSE.txt
Requires-Dist: pandas<3.0.0,>=1.0.0
Requires-Dist: click<8.1.8,>=8.0.0
Requires-Dist: requests<3.0.0,>=2.0.0
Requires-Dist: tenacity<9.0.0,>=8.0.0
Requires-Dist: tqdm<5.0.0,>=4.0.0
Requires-Dist: typeguard<5,>=4
Requires-Dist: typing-extensions<5.0.0,>=4.5.0
Requires-Dist: pyparsing<4.0.0,>=3.0.0
Requires-Dist: websocket-client<2.0.0,>=1.0.0
Requires-Dist: cuid<0.5,>=0.4
Requires-Dist: urllib3<3,>=1.26
Requires-Dist: gql[requests,websockets]<4.0.0,>=3.5.0b5
Requires-Dist: filelock<4.0.0,>=3.0.0
Requires-Dist: pip-system-certs<5.0.0,>=4.0.0; platform_system == "Windows"
Requires-Dist: pyrate-limiter<4,>=3
Requires-Dist: kili-formats==1.1.0
Provides-Extra: dev
Requires-Dist: bump2version; extra == "dev"
Requires-Dist: pytest; extra == "dev"
Requires-Dist: pytest-mock; extra == "dev"
Requires-Dist: pytest-cov; extra == "dev"
Requires-Dist: pytest-xdist[psutil]; extra == "dev"
Requires-Dist: pytest-timeout; extra == "dev"
Requires-Dist: mkdocs; extra == "dev"
Requires-Dist: mkdocs-material; extra == "dev"
Requires-Dist: mkdocstrings; extra == "dev"
Requires-Dist: mkdocstrings-python-legacy; extra == "dev"
Requires-Dist: mkdocs-click; extra == "dev"
Requires-Dist: mike; extra == "dev"
Requires-Dist: pymdown-extensions; extra == "dev"
Requires-Dist: pre-commit<4.0.0,>=3.3.0; extra == "dev"
Requires-Dist: pylint==4.0.3; extra == "dev"
Requires-Dist: pyright==1.1.407; extra == "dev"
Requires-Dist: nbformat; extra == "dev"
Requires-Dist: nbconvert; extra == "dev"
Requires-Dist: ipykernel; extra == "dev"
Requires-Dist: kili-formats[all]==1.1.0; extra == "dev"
Requires-Dist: opencv-python<5.0.0,>=4.0.0; extra == "dev"
Requires-Dist: azure-storage-blob<13.0.0,>=12.0.0; extra == "dev"
Requires-Dist: pyproj==3.7.1; extra == "dev"
Requires-Dist: shapely<3,>=1.8; extra == "dev"
Requires-Dist: tabulate<0.10.0,>=0.9.0; extra == "dev"
Requires-Dist: pyyaml<7.0,>=6.0; extra == "dev"
Requires-Dist: Pillow<11.0.0,>=9.0.0; extra == "dev"
Provides-Extra: all
Requires-Dist: azure-storage-blob<13.0.0,>=12.0.0; extra == "all"
Requires-Dist: kili-formats[all]==1.1.0; extra == "all"
Requires-Dist: opencv-python<5.0.0,>=4.0.0; extra == "all"
Requires-Dist: Pillow<11.0.0,>=9.0.0; extra == "all"
Requires-Dist: pyproj==3.7.1; extra == "all"
Requires-Dist: pyyaml<7.0,>=6.0; extra == "all"
Requires-Dist: shapely<3,>=1.8; extra == "all"
Requires-Dist: tabulate<0.10.0,>=0.9.0; extra == "all"
Provides-Extra: azure
Requires-Dist: azure-storage-blob<13.0.0,>=12.0.0; extra == "azure"
Provides-Extra: cli
Requires-Dist: tabulate<0.10.0,>=0.9.0; extra == "cli"
Provides-Extra: coco
Requires-Dist: kili-formats[coco]==1.1.0; extra == "coco"
Provides-Extra: gis
Requires-Dist: pyproj==3.7.1; extra == "gis"
Requires-Dist: shapely<3,>=1.8; extra == "gis"
Provides-Extra: image
Requires-Dist: Pillow<11.0.0,>=9.0.0; extra == "image"
Requires-Dist: kili-formats[image]==1.1.0; extra == "image"
Provides-Extra: image-utils
Requires-Dist: opencv-python<5.0.0,>=4.0.0; extra == "image-utils"
Provides-Extra: video
Requires-Dist: kili-formats[video]==1.1.0; extra == "video"
Provides-Extra: yolo
Requires-Dist: pyyaml<7.0,>=6.0; extra == "yolo"
Dynamic: license-file
